{"items": [{"id": 9, "started_at": "2026-04-13T22:04:41.421189", "finished_at": "2026-04-13T22:05:15.954180", "status": "completed", "platforms_total": 2, "platforms_scanned": 2, "platforms_success": 2, "platforms_empty": 0, "platforms_error": 0, "new_listings": 6, "total_listings": 46, "duration_seconds": 34.53}, {"id": 8, "started_at": "2026-04-13T21:50:58.866563", "finished_at": "2026-04-13T21:51:18.336938", "status": "completed", "platforms_total": 3, "platforms_scanned": 3, "platforms_success": 2, "platforms_empty": 1, "platforms_error": 0, "new_listings": 5, "total_listings": 15, "duration_seconds": 19.47}, {"id": 7, "started_at": "2026-04-13T21:48:48.305017", "finished_at": "2026-04-13T21:50:24.038930", "status": "completed_with_errors", "platforms_total": 71, "platforms_scanned": 71, "platforms_success": 34, "platforms_empty": 27, "platforms_error": 10, "new_listings": 71, "total_listings": 727, "duration_seconds": 95.73}, {"id": 6, "started_at": "2026-04-13T09:38:00.398275", "finished_at": "2026-04-13T09:39:32.798694", "status": "completed_with_errors", "platforms_total": 101, "platforms_scanned": 101, "platforms_success": 36, "platforms_empty": 44, "platforms_error": 21, "new_listings": 15, "total_listings": 779, "duration_seconds": 92.4}, {"id": 5, "started_at": "2026-04-13T08:45:27.086239", "finished_at": "2026-04-13T08:46:15.266142", "status": "completed_with_errors", "platforms_total": 3, "platforms_scanned": 3, "platforms_success": 2, "platforms_empty": 0, "platforms_error": 1, "new_listings": 15, "total_listings": 62, "duration_seconds": 48.18}, {"id": 4, "started_at": "2026-04-13T08:39:36.472367", "finished_at": "2026-04-13T08:40:18.286660", "status": "completed", "platforms_total": 5, "platforms_scanned": 5, "platforms_success": 4, "platforms_empty": 1, "platforms_error": 0, "new_listings": 6, "total_listings": 64, "duration_seconds": 41.81}, {"id": 3, "started_at": "2026-04-12T20:05:24.631895", "finished_at": "2026-04-12T20:05:30.295927", "status": "completed_with_errors", "platforms_total": 3, "platforms_scanned": 3, "platforms_success": 1, "platforms_empty": 1, "platforms_error": 1, "new_listings": 0, "total_listings": 29, "duration_seconds": 5.66}, {"id": 2, "started_at": "2026-04-12T20:00:22.806743", "finished_at": "2026-04-12T20:02:11.673961", "status": "completed_with_errors", "platforms_total": 100, "platforms_scanned": 100, "platforms_success": 33, "platforms_empty": 41, "platforms_error": 26, "new_listings": 3, "total_listings": 772, "duration_seconds": 108.87}, {"id": 1, "started_at": "2026-04-12T17:36:49.857486", "finished_at": "2026-04-12T17:38:24.423443", "status": "completed_with_errors", "platforms_total": 103, "platforms_scanned": 103, "platforms_success": 32, "platforms_empty": 41, "platforms_error": 30, "new_listings": 6, "total_listings": 765, "duration_seconds": 94.57}], "count": 9}