{"items": [{"id": 307, "scan_run_id": 6, "country_code": "ZA", "platform_name": "AgriMag.co.za", "search_url": "https://www.agrimag.co.za/tractors?q=mb+trac", "status": "error", "error_message": "403 Client Error: Forbidden for url: https://www.agrimag.co.za/tractors?q=mb+trac", "listings_found": 0, "new_listings": 0, "duration_seconds": 6.41, "created_at": "2026-04-13 09:39:25"}, {"id": 255, "scan_run_id": 6, "country_code": "FR", "platform_name": "Agriaffaires FR", "search_url": "https://www.agriaffaires.com/occasion/tracteur-agricole/1/m.ht", "status": "error", "error_message": "403 Client Error: Forbidden for url: https://www.agriaffaires.com/occasion/tracteur-agricole/1/m.ht", "listings_found": 0, "new_listings": 0, "duration_seconds": 4.52, "created_at": "2026-04-13 09:38:41"}, {"id": 314, "scan_run_id": 6, "country_code": "AR", "platform_name": "Agrofy.com.ar", "search_url": "https://www.agrofy.com.ar/tractores?q=mb+trac", "status": "error", "error_message": "403 Client Error: Forbidden for url: https://www.agrofy.com.ar/tractores?q=mb+trac", "listings_found": 0, "new_listings": 0, "duration_seconds": 5.08, "created_at": "2026-04-13 09:39:30"}, {"id": 293, "scan_run_id": 6, "country_code": "PL", "platform_name": "Allegro.pl", "search_url": "https://allegro.pl/listing?string=mb%20trac", "status": "error", "error_message": "HTTPSConnectionPool(host='allegro.pl', port=443): Read timed out. (read timeout=30)", "listings_found": 0, "new_listings": 0, "duration_seconds": 33.59, "created_at": "2026-04-13 09:39:13"}, {"id": 250, "scan_run_id": 6, "country_code": "UK", "platform_name": "Auto Trader Farm", "search_url": "https://www.autotrader.co.uk/farm", "status": "error", "error_message": "403 Client Error: Forbidden for url: https://www.autotrader.co.uk/farm", "listings_found": 0, "new_listings": 0, "duration_seconds": 3.22, "created_at": "2026-04-13 09:38:36"}, {"id": 295, "scan_run_id": 6, "country_code": "EE", "platform_name": "Auto24.ee", "search_url": "https://www.auto24.ee/", "status": "error", "error_message": "403 Client Error: Forbidden for url: https://www.auto24.ee/", "listings_found": 0, "new_listings": 0, "duration_seconds": 3.12, "created_at": "2026-04-13 09:39:15"}, {"id": 302, "scan_run_id": 6, "country_code": "LT", "platform_name": "Autoplius.lt", "search_url": "https://www.autoplius.lt/skelbimai/naudoti-traktoriai", "status": "error", "error_message": "403 Client Error: Forbidden for url: https://www.autoplius.lt/skelbimai/naudoti-traktoriai", "listings_found": 0, "new_listings": 0, "duration_seconds": 5.15, "created_at": "2026-04-13 09:39:21"}, {"id": 291, "scan_run_id": 6, "country_code": "SI", "platform_name": "Avto.net", "search_url": "https://www.avto.net/Ads/results.asp", "status": "error", "error_message": "403 Client Error: Forbidden for url: https://www.avto.net/Ads/results.asp", "listings_found": 0, "new_listings": 0, "duration_seconds": 5.13, "created_at": "2026-04-13 09:39:12"}, {"id": 252, "scan_run_id": 6, "country_code": "IE", "platform_name": "DoneDeal", "search_url": "https://www.donedeal.ie/farming?words=mb%20trac", "status": "error", "error_message": "403 Client Error: Forbidden for url: https://www.donedeal.ie/farming?words=mb%20trac", "listings_found": 0, "new_listings": 0, "duration_seconds": 4.44, "created_at": "2026-04-13 09:38:39"}, {"id": 309, "scan_run_id": 6, "country_code": "US", "platform_name": "FastlineAuctions.com", "search_url": "https://www.fastline.com/search?q=mb+trac&category=tractors", "status": "error", "error_message": "403 Client Error: Forbidden for url: https://www.fastline.com/search?q=mb+trac&category=tractors", "listings_found": 0, "new_listings": 0, "duration_seconds": 3.6, "created_at": "2026-04-13 09:39:26"}, {"id": 305, "scan_run_id": 6, "country_code": "AU", "platform_name": "Gumtree.com.au", "search_url": "https://www.gumtree.com.au/s-farming-vehicles/mb+trac/k0c18626", "status": "error", "error_message": "403 Client Error: Forbidden for url: https://www.gumtree.com.au/s-farming-vehicles/mb+trac/k0c18626", "listings_found": 0, "new_listings": 0, "duration_seconds": 3.72, "created_at": "2026-04-13 09:39:22"}, {"id": 279, "scan_run_id": 6, "country_code": "BG", "platform_name": "Mobile.bg", "search_url": "https://www.mobile.bg/obiavi/agro/traktor", "status": "error", "error_message": "403 Client Error: Forbidden for url: https://www.mobile.bg/obiavi/agro/traktor", "listings_found": 0, "new_listings": 0, "duration_seconds": 4.45, "created_at": "2026-04-13 09:39:01"}, {"id": 315, "scan_run_id": 6, "country_code": "BR", "platform_name": "OLX.com.br", "search_url": "https://www.olx.com.br/brasil?q=mb+trac", "status": "error", "error_message": "403 Client Error: Forbidden for url: https://www.olx.com.br/brasil?q=mb+trac", "listings_found": 0, "new_listings": 0, "duration_seconds": 5.56, "created_at": "2026-04-13 09:39:32"}, {"id": 297, "scan_run_id": 6, "country_code": "EE", "platform_name": "Osta.ee", "search_url": "https://www.osta.ee/search/?q=mb+trac", "status": "error", "error_message": "403 Client Error: Forbidden for url: https://www.osta.ee/search/?q=mb+trac", "listings_found": 0, "new_listings": 0, "duration_seconds": 5.98, "created_at": "2026-04-13 09:39:17"}, {"id": 288, "scan_run_id": 6, "country_code": "RS", "platform_name": "Polovniautomobili.com", "search_url": "https://www.polovniautomobili.com/traktori", "status": "error", "error_message": "403 Client Error: Forbidden for url: https://www.polovniautomobili.com/traktori", "listings_found": 0, "new_listings": 0, "duration_seconds": 4.14, "created_at": "2026-04-13 09:39:09"}, {"id": 227, "scan_run_id": 6, "country_code": "CH", "platform_name": "Ricardo.ch", "search_url": "https://www.ricardo.ch/de/s/mb%20trac/", "status": "error", "error_message": "403 Client Error: Forbidden for url: https://www.ricardo.ch/de/s/mb%20trac/", "listings_found": 0, "new_listings": 0, "duration_seconds": 4.48, "created_at": "2026-04-13 09:38:14"}, {"id": 299, "scan_run_id": 6, "country_code": "LT", "platform_name": "Skelbiu.lt", "search_url": "https://www.skelbiu.lt/skelbimai/?keywords=mb+trac", "status": "error", "error_message": "403 Client Error: Forbidden for url: https://www.skelbiu.lt/skelbimai/?keywords=mb+trac", "listings_found": 0, "new_listings": 0, "duration_seconds": 3.9, "created_at": "2026-04-13 09:39:18"}, {"id": 310, "scan_run_id": 6, "country_code": "NZ", "platform_name": "TradeMe.co.nz", "search_url": "https://www.trademe.co.nz/a/motors/farming/tractors/search?search_string=mb+trac", "status": "error", "error_message": "406 Client Error: Not Acceptable for url: https://www.trademe.co.nz/a/motors/farming/tractors/search?search_string=mb+trac", "listings_found": 0, "new_listings": 0, "duration_seconds": 5.09, "created_at": "2026-04-13 09:39:27"}, {"id": 273, "scan_run_id": 6, "country_code": "HU", "platform_name": "Traktorpool.hu", "search_url": "https://www.traktorpool.hu/", "status": "error", "error_message": "403 Client Error: Forbidden for url: https://www.traktorpool.hu/", "listings_found": 0, "new_listings": 0, "duration_seconds": 3.79, "created_at": "2026-04-13 09:38:56"}, {"id": 231, "scan_run_id": 6, "country_code": "CH", "platform_name": "Tutti.ch", "search_url": "https://www.tutti.ch/de/q/suche/Ak6dtYiB0cmFjwJTAwMDA?sorting=newest&page=1&query=mb+trac", "status": "error", "error_message": "403 Client Error: Forbidden for url: https://www.tutti.ch/de/q/suche/Ak6dtYiB0cmFjwJTAwMDA?sorting=newest&page=1&query=mb+trac", "listings_found": 0, "new_listings": 0, "duration_seconds": 5.05, "created_at": "2026-04-13 09:38:18"}, {"id": 225, "scan_run_id": 6, "country_code": "AT", "platform_name": "Willhaben.at", "search_url": "https://www.willhaben.at/iad/kaufen-und-verkaufen/marktplatz?keyword=mb+trac", "status": "error", "error_message": "403 Client Error: Forbidden for url: https://www.willhaben.at/iad/kaufen-und-verkaufen/marktplatz?keyword=mb+trac", "listings_found": 0, "new_listings": 0, "duration_seconds": 5.23, "created_at": "2026-04-13 09:38:12"}, {"id": 280, "scan_run_id": 6, "country_code": "UA", "platform_name": "AGRO.RIA", "search_url": "https://agro.ria.com/", "status": "empty", "error_message": null, "listings_found": 0, "new_listings": 0, "duration_seconds": 0.4, "created_at": "2026-04-13 09:39:02"}, {"id": 228, "scan_run_id": 6, "country_code": "DE", "platform_name": "Agriaffaires", "search_url": "https://www.agriaffaires.de/gebrauchte/landmaschinen/1-deutschland.html", "status": "empty", "error_message": null, "listings_found": 0, "new_listings": 0, "duration_seconds": 7.35, "created_at": "2026-04-13 09:38:15"}, {"id": 278, "scan_run_id": 6, "country_code": "BG", "platform_name": "Auto.bg", "search_url": "https://www.auto.bg/obiavi/agro/traktor", "status": "empty", "error_message": null, "listings_found": 0, "new_listings": 0, "duration_seconds": 0.86, "created_at": "2026-04-13 09:39:00"}, {"id": 274, "scan_run_id": 6, "country_code": "RO", "platform_name": "Autovit.ro", "search_url": "https://www.autovit.ro/utilaje-agricole/tractoare", "status": "empty", "error_message": null, "listings_found": 0, "new_listings": 0, "duration_seconds": 1.11, "created_at": "2026-04-13 09:38:56"}, {"id": 265, "scan_run_id": 6, "country_code": "CZ", "platform_name": "Bazos.cz", "search_url": "https://stroje.bazos.cz/?hledat=mb+trac", "status": "empty", "error_message": null, "listings_found": 0, "new_listings": 0, "duration_seconds": 0.35, "created_at": "2026-04-13 09:38:51"}, {"id": 268, "scan_run_id": 6, "country_code": "SK", "platform_name": "Bazos.sk", "search_url": "https://stroje.bazos.sk/?hladat=mb+trac", "status": "empty", "error_message": null, "listings_found": 0, "new_listings": 0, "duration_seconds": 0.36, "created_at": "2026-04-13 09:38:52"}, {"id": 233, "scan_run_id": 6, "country_code": "SE", "platform_name": "Blocket.se", "search_url": "https://www.blocket.se/annonser/hela_sverige?q=mb+trac", "status": "empty", "error_message": null, "listings_found": 0, "new_listings": 0, "duration_seconds": 0.16, "created_at": "2026-04-13 09:38:20"}, {"id": 286, "scan_run_id": 6, "country_code": "SI", "platform_name": "Bolha.com", "search_url": "https://www.bolha.com/search/?keywords=mb+trac", "status": "empty", "error_message": null, "listings_found": 0, "new_listings": 0, "duration_seconds": 0.47, "created_at": "2026-04-13 09:39:07"}, {"id": 259, "scan_run_id": 6, "country_code": "PT", "platform_name": "CustoJusto", "search_url": "https://www.custojusto.pt/portugal/q/mb+trac", "status": "empty", "error_message": null, "listings_found": 0, "new_listings": 0, "duration_seconds": 2.53, "created_at": "2026-04-13 09:38:46"}, {"id": 241, "scan_run_id": 6, "country_code": "DK", "platform_name": "DBA.dk", "search_url": "https://www.dba.dk/soeg/?soeg=mb+trac", "status": "empty", "error_message": null, "listings_found": 0, "new_listings": 0, "duration_seconds": 0.21, "created_at": "2026-04-13 09:38:29"}, {"id": 249, "scan_run_id": 6, "country_code": "IE", "platform_name": "Farm And Plant", "search_url": "https://www.farmandplant.ie/", "status": "empty", "error_message": null, "listings_found": 0, "new_listings": 0, "duration_seconds": 1.68, "created_at": "2026-04-13 09:38:35"}, {"id": 247, "scan_run_id": 6, "country_code": "UK", "platform_name": "Farmers Weekly", "search_url": "https://classified.fwi.co.uk/", "status": "empty", "error_message": null, "listings_found": 0, "new_listings": 0, "duration_seconds": 0.88, "created_at": "2026-04-13 09:38:33"}, {"id": 232, "scan_run_id": 6, "country_code": "NO", "platform_name": "Finn.no", "search_url": "https://www.finn.no/bap/forsale/search.html?q=mb+trac", "status": "empty", "error_message": null, "listings_found": 0, "new_listings": 0, "duration_seconds": 0.19, "created_at": "2026-04-13 09:38:19"}, {"id": 243, "scan_run_id": 6, "country_code": "UK", "platform_name": "Gumtree", "search_url": "https://www.gumtree.com/search?q=mb+trac", "status": "empty", "error_message": null, "listings_found": 0, "new_listings": 0, "duration_seconds": 0.8, "created_at": "2026-04-13 09:38:31"}, {"id": 270, "scan_run_id": 6, "country_code": "HU", "platform_name": "Jófogás", "search_url": "https://www.jofogas.hu/magyarorszag?q=mb+trac", "status": "empty", "error_message": null, "listings_found": 0, "new_listings": 0, "duration_seconds": 0.28, "created_at": "2026-04-13 09:38:54"}, {"id": 306, "scan_run_id": 6, "country_code": "CA", "platform_name": "Kijiji.ca", "search_url": "https://www.kijiji.ca/b-farming-equipment/canada/mb-trac/k0c172l0", "status": "empty", "error_message": null, "listings_found": 0, "new_listings": 0, "duration_seconds": 0.57, "created_at": "2026-04-13 09:39:23"}, {"id": 283, "scan_run_id": 6, "country_code": "RS", "platform_name": "KupujemProdajem", "search_url": "https://www.kupujemprodajem.com/pretraga?keywords=mb+trac", "status": "empty", "error_message": null, "listings_found": 0, "new_listings": 0, "duration_seconds": 0.74, "created_at": "2026-04-13 09:39:04"}, {"id": 219, "scan_run_id": 6, "country_code": "DE", "platform_name": "Landwirt.com", "search_url": "https://www.landwirt.com/en/classifieds/tractors/agricultural-tractors/mercedes", "status": "empty", "error_message": null, "listings_found": 0, "new_listings": 0, "duration_seconds": 1.33, "created_at": "2026-04-13 09:38:05"}, {"id": 304, "scan_run_id": 6, "country_code": "US", "platform_name": "MachineryTrader.com", "search_url": "https://www.machinerytrader.com/listings/farm-equipment/for-sale/list?keywords=mb%20trac", "status": "empty", "error_message": null, "listings_found": 0, "new_listings": 0, "duration_seconds": 0.31, "created_at": "2026-04-13 09:39:22"}, {"id": 301, "scan_run_id": 6, "country_code": "AU", "platform_name": "Machines4U.com.au", "search_url": "https://www.machines4u.com.au/search/Tractors/mb-trac", "status": "empty", "error_message": null, "listings_found": 0, "new_listings": 0, "duration_seconds": 1.46, "created_at": "2026-04-13 09:39:20"}, {"id": 313, "scan_run_id": 6, "country_code": "NA", "platform_name": "MarketBook.na", "search_url": "https://www.marketbook.com.na/listings/search?Category=1100&keywords=mb%20trac", "status": "empty", "error_message": null, "listings_found": 0, "new_listings": 0, "duration_seconds": 0.29, "created_at": "2026-04-13 09:39:30"}, {"id": 222, "scan_run_id": 6, "country_code": "AT", "platform_name": "Maschinensucher.at", "search_url": "https://www.maschinensucher.at/mss/mb+trac", "status": "empty", "error_message": null, "listings_found": 0, "new_listings": 0, "duration_seconds": 0.65, "created_at": "2026-04-13 09:38:09"}, {"id": 258, "scan_run_id": 6, "country_code": "IT", "platform_name": "Mascus.it", "search_url": "https://www.mascus.it/mb%20trac/+/1,relevance,search.html", "status": "empty", "error_message": null, "listings_found": 0, "new_listings": 0, "duration_seconds": 0.3, "created_at": "2026-04-13 09:38:45"}, {"id": 311, "scan_run_id": 6, "country_code": "AR", "platform_name": "MercadoLibre.com.ar", "search_url": "https://listado.mercadolibre.com.ar/mb-trac", "status": "empty", "error_message": null, "listings_found": 0, "new_listings": 0, "duration_seconds": 1.69, "created_at": "2026-04-13 09:39:28"}, {"id": 312, "scan_run_id": 6, "country_code": "BR", "platform_name": "MercadoLivre.com.br", "search_url": "https://lista.mercadolivre.com.br/mb-trac", "status": "empty", "error_message": null, "listings_found": 0, "new_listings": 0, "duration_seconds": 0.71, "created_at": "2026-04-13 09:39:28"}, {"id": 238, "scan_run_id": 6, "country_code": "FI", "platform_name": "Nettikone.com", "search_url": "https://www.nettikone.com/maatalouskoneet/traktorit", "status": "empty", "error_message": null, "listings_found": 0, "new_listings": 0, "duration_seconds": 1.68, "created_at": "2026-04-13 09:38:25"}, {"id": 256, "scan_run_id": 6, "country_code": "PT", "platform_name": "OLX Portugal", "search_url": "https://www.olx.pt/ads/q-mb-trac/", "status": "empty", "error_message": null, "listings_found": 0, "new_listings": 0, "duration_seconds": 1.68, "created_at": "2026-04-13 09:38:43"}, {"id": 277, "scan_run_id": 6, "country_code": "BG", "platform_name": "OLX.bg", "search_url": "https://www.olx.bg/ads/q-mb-trac/", "status": "empty", "error_message": null, "listings_found": 0, "new_listings": 0, "duration_seconds": 1.16, "created_at": "2026-04-13 09:38:59"}, {"id": 261, "scan_run_id": 6, "country_code": "PL", "platform_name": "OLX.pl", "search_url": "https://www.olx.pl/rolnictwo/ciagniki/q-mb-trac/", "status": "empty", "error_message": null, "listings_found": 0, "new_listings": 0, "duration_seconds": 1.62, "created_at": "2026-04-13 09:38:47"}, {"id": 275, "scan_run_id": 6, "country_code": "RO", "platform_name": "OLX.ro", "search_url": "https://www.olx.ro/oferte/q-mb-trac/", "status": "empty", "error_message": null, "listings_found": 0, "new_listings": 0, "duration_seconds": 1.79, "created_at": "2026-04-13 09:38:57"}, {"id": 282, "scan_run_id": 6, "country_code": "UA", "platform_name": "OLX.ua", "search_url": "https://www.olx.ua/uk/transport/selhoztehnika/q-mb-trac/", "status": "empty", "error_message": null, "listings_found": 0, "new_listings": 0, "duration_seconds": 2.88, "created_at": "2026-04-13 09:39:04"}, {"id": 292, "scan_run_id": 6, "country_code": "LV", "platform_name": "SS.lv", "search_url": "https://www.ss.lv/lv/agriculture/agricultural-machinery/tractors/", "status": "empty", "error_message": null, "listings_found": 0, "new_listings": 0, "duration_seconds": 0.33, "created_at": "2026-04-13 09:39:12"}, {"id": 267, "scan_run_id": 6, "country_code": "CZ", "platform_name": "Sbazar.cz", "search_url": "https://www.sbazar.cz/hledej/mb+trac", "status": "empty", "error_message": null, "listings_found": 0, "new_listings": 0, "duration_seconds": 1.1, "created_at": "2026-04-13 09:38:52"}, {"id": 217, "scan_run_id": 6, "country_code": "DE", "platform_name": "Technikboerse", "search_url": "https://www.technikboerse.com/en/marke/mercedes-benz-791", "status": "empty", "error_message": null, "listings_found": 0, "new_listings": 0, "duration_seconds": 1.11, "created_at": "2026-04-13 09:38:03"}, {"id": 303, "scan_run_id": 6, "country_code": "US", "platform_name": "TractorHouse.com", "search_url": "https://www.tractorhouse.com/listings/farm-equipment/for-sale/list?keywords=mb%20trac", "status": "empty", "error_message": null, "listings_found": 0, "new_listings": 0, "duration_seconds": 0.28, "created_at": "2026-04-13 09:39:21"}, {"id": 308, "scan_run_id": 6, "country_code": "CA", "platform_name": "TractorHouse.com (CA)", "search_url": "https://www.tractorhouse.com/listings/farm-equipment/for-sale/list?keywords=mb%20trac&country=CAN", "status": "empty", "error_message": null, "listings_found": 0, "new_listings": 0, "duration_seconds": 0.26, "created_at": "2026-04-13 09:39:26"}, {"id": 223, "scan_run_id": 6, "country_code": "AT", "platform_name": "Traktorpool.at", "search_url": "https://www.traktorpool.at/gebraucht/a-Traktoren/24/c-MercedesBenz/337/", "status": "empty", "error_message": null, "listings_found": 0, "new_listings": 0, "duration_seconds": 1.52, "created_at": "2026-04-13 09:38:10"}, {"id": 224, "scan_run_id": 6, "country_code": "CH", "platform_name": "Traktorpool.ch", "search_url": "https://www.traktorpool.ch/gebraucht/a-Traktoren/24/c-MercedesBenz/337/", "status": "empty", "error_message": null, "listings_found": 0, "new_listings": 0, "duration_seconds": 1.57, "created_at": "2026-04-13 09:38:11"}, {"id": 218, "scan_run_id": 6, "country_code": "DE", "platform_name": "Traktorpool.de", "search_url": "https://www.traktorpool.de/gebraucht/a-Traktoren/24/b-Traktoren/95/c-MercedesBenz/337/model/MB+Trac/", "status": "empty", "error_message": null, "listings_found": 0, "new_listings": 0, "duration_seconds": 1.48, "created_at": "2026-04-13 09:38:04"}, {"id": 246, "scan_run_id": 6, "country_code": "DK", "platform_name": "Traktorpool.dk", "search_url": "https://www.traktorpool.dk/brugt/a-Traktorer/24/c-MercedesBenz/337/model/MB+Trac/", "status": "empty", "error_message": null, "listings_found": 0, "new_listings": 0, "duration_seconds": 1.64, "created_at": "2026-04-13 09:38:33"}, {"id": 239, "scan_run_id": 6, "country_code": "FI", "platform_name": "Traktorpool.fi", "search_url": "https://www.traktorpool.fi/käytetty/a-Traktorit/24/", "status": "empty", "error_message": null, "listings_found": 0, "new_listings": 0, "duration_seconds": 1.61, "created_at": "2026-04-13 09:38:26"}, {"id": 242, "scan_run_id": 6, "country_code": "SE", "platform_name": "Traktorpool.se", "search_url": "https://www.traktorpool.se/begagnat/a-Traktorer/24/c-MercedesBenz/337/", "status": "empty", "error_message": null, "listings_found": 0, "new_listings": 0, "duration_seconds": 2.75, "created_at": "2026-04-13 09:38:29"}, {"id": 220, "scan_run_id": 6, "country_code": "DE", "platform_name": "TruckScout24", "search_url": "https://www.truckscout24.de/landmaschinen/gebraucht/alle/mercedes-benz/mb-trac", "status": "empty", "error_message": null, "listings_found": 0, "new_listings": 0, "duration_seconds": 0.81, "created_at": "2026-04-13 09:38:07"}, {"id": 300, "scan_run_id": 6, "country_code": "ZA", "platform_name": "TruckTrader.co.za", "search_url": "https://www.trucktrader.co.za/search?q=mb+trac", "status": "empty", "error_message": null, "listings_found": 0, "new_listings": 0, "duration_seconds": 0.95, "created_at": "2026-04-13 09:39:19"}, {"id": 234, "scan_run_id": 6, "country_code": "BE", "platform_name": "2dehands.be", "search_url": "https://www.2dehands.be/q/mb+trac/", "status": "success", "error_message": null, "listings_found": 2, "new_listings": 0, "duration_seconds": 0.94, "created_at": "2026-04-13 09:38:21"}, {"id": 287, "scan_run_id": 6, "country_code": "GR", "platform_name": "Car.gr", "search_url": "https://www.car.gr/classifieds/tractors/?category=15420&variant=trac", "status": "success", "error_message": null, "listings_found": 3, "new_listings": 0, "duration_seconds": 33.71, "created_at": "2026-04-13 09:39:08"}, {"id": 298, "scan_run_id": 6, "country_code": "ZA", "platform_name": "Gumtree.co.za", "search_url": "https://www.gumtree.co.za/s-all-the-ads/v1b0p1?q=mb+trac", "status": "success", "error_message": null, "listings_found": 3, "new_listings": 0, "duration_seconds": 0.79, "created_at": "2026-04-13 09:39:18"}, {"id": 253, "scan_run_id": 6, "country_code": "FR", "platform_name": "Leboncoin", "search_url": "https://www.leboncoin.fr/recherche?text=mb%20trac", "status": "success", "error_message": null, "listings_found": 33, "new_listings": 0, "duration_seconds": 3.96, "created_at": "2026-04-13 09:38:39"}, {"id": 226, "scan_run_id": 6, "country_code": "NL", "platform_name": "Marktplaats", "search_url": "https://www.marktplaats.nl/q/mb+trac/", "status": "success", "error_message": null, "listings_found": 2, "new_listings": 0, "duration_seconds": 0.76, "created_at": "2026-04-13 09:38:13"}, {"id": 248, "scan_run_id": 6, "country_code": "IE", "platform_name": "Mascus Ireland", "search_url": "https://www.mascus.ie/mb%20trac/+/1,relevance,search.html", "status": "success", "error_message": null, "listings_found": 29, "new_listings": 0, "duration_seconds": 0.81, "created_at": "2026-04-13 09:38:34"}, {"id": 245, "scan_run_id": 6, "country_code": "UK", "platform_name": "Mascus UK", "search_url": "https://www.mascus.co.uk/mb%20trac/+/1,relevance,search.html", "status": "success", "error_message": null, "listings_found": 29, "new_listings": 0, "duration_seconds": 0.77, "created_at": "2026-04-13 09:38:32"}, {"id": 235, "scan_run_id": 6, "country_code": "BE", "platform_name": "Mascus.be", "search_url": "https://www.mascus.be/mb%20trac/+/1,relevance,search.html", "status": "success", "error_message": null, "listings_found": 29, "new_listings": 0, "duration_seconds": 1.05, "created_at": "2026-04-13 09:38:22"}, {"id": 266, "scan_run_id": 6, "country_code": "CZ", "platform_name": "Mascus.cz", "search_url": "https://www.mascus.cz/mb%20trac/+/1,relevance,search.html", "status": "success", "error_message": null, "listings_found": 29, "new_listings": 0, "duration_seconds": 0.75, "created_at": "2026-04-13 09:38:51"}, {"id": 221, "scan_run_id": 6, "country_code": "DE", "platform_name": "Mascus.de", "search_url": "https://www.mascus.de/mb%20trac/+/1,relevance,search.html", "status": "success", "error_message": null, "listings_found": 29, "new_listings": 0, "duration_seconds": 1.2, "created_at": "2026-04-13 09:38:08"}, {"id": 244, "scan_run_id": 6, "country_code": "DK", "platform_name": "Mascus.dk", "search_url": "https://www.mascus.dk/mb%20trac/+/1,relevance,search.html", "status": "success", "error_message": null, "listings_found": 30, "new_listings": 0, "duration_seconds": 1.01, "created_at": "2026-04-13 09:38:31"}, {"id": 290, "scan_run_id": 6, "country_code": "EE", "platform_name": "Mascus.ee", "search_url": "https://www.mascus.ee/mb%20trac/+/1,relevance,search.html", "status": "success", "error_message": null, "listings_found": 29, "new_listings": 0, "duration_seconds": 0.63, "created_at": "2026-04-13 09:39:10"}, {"id": 254, "scan_run_id": 6, "country_code": "ES", "platform_name": "Mascus.es", "search_url": "https://www.mascus.es/mb%20trac/+/1,relevance,search.html", "status": "success", "error_message": null, "listings_found": 29, "new_listings": 0, "duration_seconds": 1.18, "created_at": "2026-04-13 09:38:40"}, {"id": 240, "scan_run_id": 6, "country_code": "FI", "platform_name": "Mascus.fi", "search_url": "https://www.mascus.fi/mb%20trac/+/1,relevance,search.html", "status": "success", "error_message": null, "listings_found": 29, "new_listings": 0, "duration_seconds": 0.88, "created_at": "2026-04-13 09:38:27"}, {"id": 251, "scan_run_id": 6, "country_code": "FR", "platform_name": "Mascus.fr", "search_url": "https://www.mascus.fr/mb%20trac/+/1,relevance,search.html", "status": "success", "error_message": null, "listings_found": 29, "new_listings": 0, "duration_seconds": 0.8, "created_at": "2026-04-13 09:38:37"}, {"id": 260, "scan_run_id": 6, "country_code": "GR", "platform_name": "Mascus.gr", "search_url": "https://www.mascus.gr/mb%20trac/+/1,relevance,search.html", "status": "success", "error_message": null, "listings_found": 29, "new_listings": 0, "duration_seconds": 1.1, "created_at": "2026-04-13 09:38:47"}, {"id": 284, "scan_run_id": 6, "country_code": "HR", "platform_name": "Mascus.hr", "search_url": "https://www.mascus.hr/mb%20trac/+/1,relevance,search.html", "status": "success", "error_message": null, "listings_found": 29, "new_listings": 0, "duration_seconds": 1.19, "created_at": "2026-04-13 09:39:05"}, {"id": 271, "scan_run_id": 6, "country_code": "HU", "platform_name": "Mascus.hu", "search_url": "https://www.mascus.hu/mb%20trac/+/1,relevance,search.html", "status": "success", "error_message": null, "listings_found": 29, "new_listings": 0, "duration_seconds": 0.84, "created_at": "2026-04-13 09:38:54"}, {"id": 296, "scan_run_id": 6, "country_code": "LT", "platform_name": "Mascus.lt", "search_url": "https://www.mascus.lt/mb%20trac/+/1,relevance,search.html", "status": "success", "error_message": null, "listings_found": 29, "new_listings": 0, "duration_seconds": 1.03, "created_at": "2026-04-13 09:39:16"}, {"id": 294, "scan_run_id": 6, "country_code": "LV", "platform_name": "Mascus.lv", "search_url": "https://www.mascus.lv/mb%20trac/+/1,relevance,search.html", "status": "success", "error_message": null, "listings_found": 29, "new_listings": 0, "duration_seconds": 0.77, "created_at": "2026-04-13 09:39:14"}, {"id": 230, "scan_run_id": 6, "country_code": "NL", "platform_name": "Mascus.nl", "search_url": "https://www.mascus.nl/mb%20trac/+/1,relevance,search.html", "status": "success", "error_message": null, "listings_found": 29, "new_listings": 0, "duration_seconds": 1.24, "created_at": "2026-04-13 09:38:18"}, {"id": 236, "scan_run_id": 6, "country_code": "NO", "platform_name": "Mascus.no", "search_url": "https://www.mascus.no/mb%20trac/+/1,relevance,search.html", "status": "success", "error_message": null, "listings_found": 29, "new_listings": 0, "duration_seconds": 0.92, "created_at": "2026-04-13 09:38:23"}, {"id": 263, "scan_run_id": 6, "country_code": "PL", "platform_name": "Mascus.pl", "search_url": "https://www.mascus.pl/mb%20trac/+/1,relevance,search.html", "status": "success", "error_message": null, "listings_found": 30, "new_listings": 0, "duration_seconds": 0.93, "created_at": "2026-04-13 09:38:49"}, {"id": 276, "scan_run_id": 6, "country_code": "RO", "platform_name": "Mascus.ro", "search_url": "https://www.mascus.ro/mb%20trac/+/1,relevance,search.html", "status": "success", "error_message": null, "listings_found": 29, "new_listings": 0, "duration_seconds": 0.88, "created_at": "2026-04-13 09:38:59"}, {"id": 285, "scan_run_id": 6, "country_code": "RS", "platform_name": "Mascus.rs", "search_url": "https://www.mascus.rs/mb%20trac/+/1,relevance,search.html", "status": "success", "error_message": null, "listings_found": 30, "new_listings": 0, "duration_seconds": 0.81, "created_at": "2026-04-13 09:39:06"}, {"id": 237, "scan_run_id": 6, "country_code": "SE", "platform_name": "Mascus.se", "search_url": "https://www.mascus.se/mb%20trac/+/1,relevance,search.html", "status": "success", "error_message": null, "listings_found": 29, "new_listings": 0, "duration_seconds": 1.23, "created_at": "2026-04-13 09:38:24"}, {"id": 289, "scan_run_id": 6, "country_code": "SI", "platform_name": "Mascus.si", "search_url": "https://www.mascus.si/mb%20trac/+/1,relevance,search.html", "status": "success", "error_message": null, "listings_found": 29, "new_listings": 0, "duration_seconds": 0.94, "created_at": "2026-04-13 09:39:10"}, {"id": 269, "scan_run_id": 6, "country_code": "SK", "platform_name": "Mascus.sk", "search_url": "https://www.mascus.sk/mb%20trac/+/1,relevance,search.html", "status": "success", "error_message": null, "listings_found": 30, "new_listings": 0, "duration_seconds": 0.75, "created_at": "2026-04-13 09:38:53"}, {"id": 262, "scan_run_id": 6, "country_code": "ES", "platform_name": "MilAnuncios", "search_url": "https://www.milanuncios.com/anuncios/?s=mb%20trac&orden=relevance&fromSearch=1&fromSuggester=0&suggestionUsed=0&hitOrigin=home_search&recentSearchShowed=0&recentSearchUsed=0", "status": "success", "error_message": null, "listings_found": 3, "new_listings": 0, "duration_seconds": 16.51, "created_at": "2026-04-13 09:38:48"}, {"id": 281, "scan_run_id": 6, "country_code": "HR", "platform_name": "Njuskalo.hr", "search_url": "https://www.njuskalo.hr/traktori?keywords=mb+trac", "status": "success", "error_message": null, "listings_found": 1, "new_listings": 0, "duration_seconds": 0.86, "created_at": "2026-04-13 09:39:03"}, {"id": 264, "scan_run_id": 6, "country_code": "PL", "platform_name": "Otomoto.pl", "search_url": "https://www.otomoto.pl/maszyny-rolnicze/traktory", "status": "success", "error_message": null, "listings_found": 1, "new_listings": 0, "duration_seconds": 1.56, "created_at": "2026-04-13 09:38:50"}, {"id": 257, "scan_run_id": 6, "country_code": "IT", "platform_name": "Subito.it", "search_url": "https://www.subito.it/annunci-italia/vendita/usato/?q=mb+trac", "status": "success", "error_message": null, "listings_found": 3, "new_listings": 0, "duration_seconds": 0.67, "created_at": "2026-04-13 09:38:44"}, {"id": 229, "scan_run_id": 6, "country_code": "NL", "platform_name": "TrucksNL", "search_url": "https://www.trucksnl.com/farm-tractors/mb-trac", "status": "success", "error_message": null, "listings_found": 1, "new_listings": 0, "duration_seconds": 1.05, "created_at": "2026-04-13 09:38:17"}, {"id": 272, "scan_run_id": 6, "country_code": "ES", "platform_name": "Wallapop", "search_url": "https://es.wallapop.com/app/search?keywords=mb+trac", "status": "success", "error_message": null, "listings_found": 4, "new_listings": 4, "duration_seconds": 25.83, "created_at": "2026-04-13 09:38:55"}, {"id": 216, "scan_run_id": 6, "country_code": "DE", "platform_name": "eBay Kleinanzeigen", "search_url": "https://www.kleinanzeigen.de/s-mb-trac/k0", "status": "success", "error_message": null, "listings_found": 27, "new_listings": 10, "duration_seconds": 0.73, "created_at": "2026-04-13 09:38:02"}, {"id": 215, "scan_run_id": 6, "country_code": "DE", "platform_name": "eBay Kleinanzeigen (1600)", "search_url": "https://www.kleinanzeigen.de/s-trac-1600/k0", "status": "success", "error_message": null, "listings_found": 25, "new_listings": 1, "duration_seconds": 0.52, "created_at": "2026-04-13 09:38:01"}], "count": 101, "scan_run_id": 6}